asp_plot/__init__.py
asp_plot/alignment.py
asp_plot/altimetry.py
asp_plot/bundle_adjust.py
asp_plot/csm_camera.py
asp_plot/processing_parameters.py
asp_plot/scenes.py
asp_plot/stereo.py
asp_plot/stereo_geometry.py
asp_plot/stereopair_metadata_parser.py
asp_plot/utils.py
asp_plot/cli/__init__.py
asp_plot/cli/asp_plot.py
asp_plot/cli/csm_camera_plot.py
asp_plot/cli/stereo_geom.py
asp_plot-1.3.1.dist-info/METADATA
asp_plot-1.3.1.dist-info/WHEEL
asp_plot-1.3.1.dist-info/entry_points.txt
asp_plot-1.3.1.dist-info/licenses/LICENSE
asp_plot-1.3.1.dist-info/RECORD
