Metadata-Version: 2.4
Name: asp_plot
Version: 1.3.1
Summary: Package for plotting outputs Ames Stereo Pipeline processing
Project-URL: Homepage, https://github.com/uw-cryo/asp_plot
Project-URL: Issues, https://github.com/uw-cryo/asp_plot/issues
Author-email: Ben Purinton <purinton@uw.edu>, David Shean <dshean@uw.edu>, Shashank Bhushan <sbhusha1@umd.edu>
License: BSD-3-Clause
License-File: LICENSE
Classifier: License :: OSI Approved :: BSD License
Classifier: Operating System :: OS Independent
Classifier: Programming Language :: Python :: 3
Requires-Python: >=3.11
